t2iapi/__init__.py
t2iapi/__init__.pyi
t2iapi/basic_requests_pb2.py
t2iapi/basic_requests_pb2.pyi
t2iapi/basic_requests_pb2_grpc.py
t2iapi/basic_responses_pb2.py
t2iapi/basic_responses_pb2.pyi
t2iapi/basic_responses_pb2_grpc.py
t2iapi/response_types_pb2.py
t2iapi/response_types_pb2.pyi
t2iapi/response_types_pb2_grpc.py
t2iapi/activation_state/__init__.py
t2iapi/activation_state/__init__.pyi
t2iapi/activation_state/activation_state_requests_pb2.py
t2iapi/activation_state/activation_state_requests_pb2.pyi
t2iapi/activation_state/activation_state_requests_pb2_grpc.py
t2iapi/activation_state/service_pb2.py
t2iapi/activation_state/service_pb2.pyi
t2iapi/activation_state/service_pb2_grpc.py
t2iapi/activation_state/types_pb2.py
t2iapi/activation_state/types_pb2.pyi
t2iapi/activation_state/types_pb2_grpc.py
t2iapi/alert/__init__.py
t2iapi/alert/__init__.pyi
t2iapi/alert/alert_requests_pb2.py
t2iapi/alert/alert_requests_pb2.pyi
t2iapi/alert/alert_requests_pb2_grpc.py
t2iapi/alert/service_pb2.py
t2iapi/alert/service_pb2.pyi
t2iapi/alert/service_pb2_grpc.py
t2iapi/alert/types_pb2.py
t2iapi/alert/types_pb2.pyi
t2iapi/alert/types_pb2_grpc.py
t2iapi/biceps/__init__.py
t2iapi/biceps/__init__.pyi
t2iapi/biceps/codedvalue_pb2.py
t2iapi/biceps/codedvalue_pb2.pyi
t2iapi/biceps/codedvalue_pb2_grpc.py
t2iapi/biceps/instanceidentifier_pb2.py
t2iapi/biceps/instanceidentifier_pb2.pyi
t2iapi/biceps/instanceidentifier_pb2_grpc.py
t2iapi/biceps/localizedtext_pb2.py
t2iapi/biceps/localizedtext_pb2.pyi
t2iapi/biceps/localizedtext_pb2_grpc.py
t2iapi/biceps/localizedtextwidth_pb2.py
t2iapi/biceps/localizedtextwidth_pb2.pyi
t2iapi/biceps/localizedtextwidth_pb2_grpc.py
t2iapi/biceps/mdibversiongroup_pb2.py
t2iapi/biceps/mdibversiongroup_pb2.pyi
t2iapi/biceps/mdibversiongroup_pb2_grpc.py
t2iapi/biceps/metadata_pb2.py
t2iapi/biceps/metadata_pb2.pyi
t2iapi/biceps/metadata_pb2_grpc.py
t2iapi/combined/__init__.py
t2iapi/combined/__init__.pyi
t2iapi/combined/combined_requests_pb2.py
t2iapi-4.4.0.dist-info/LICENSE
t2iapi-4.4.0.dist-info/METADATA
t2iapi-4.4.0.dist-info/WHEEL
t2iapi-4.4.0.dist-info/top_level.txt
t2iapi-4.4.0.dist-info/zip-safe
t2iapi-4.4.0.dist-info/RECORD
