Metadata-Version: 2.1
Name: t2iapi
Version: 4.4.0
Summary: T2I API for device communication in test scenarios
Home-page: https://github.com/Draegerwerk/t2iapi
Author: T2I Team
Author-email: DLCDE-ODDS-T2I@draeger.com
License: MIT
Platform: UNKNOWN
Classifier: Development Status :: 5 - Production/Stable
Classifier: Programming Language :: Python :: 3 :: Only
Classifier: Intended Audience :: Developers
Classifier: Natural Language :: English
Classifier: Topic :: Software Development :: Testing
Classifier: License :: OSI Approved :: MIT License
Requires-Dist: protobuf (==4.25.0)
Requires-Dist: grpcio (==1.60.1)
Requires-Dist: types-protobuf
